metabolights_utils/__init__.py
metabolights_utils/common.py
metabolights_utils/isa_file_utils.py
metabolights_utils/commands/__init__.py
metabolights_utils/commands/cli.py
metabolights_utils/commands/utils.py
metabolights_utils/commands/validate_local_study.py
metabolights_utils/commands/model/__init__.py
metabolights_utils/commands/model/model_cli.py
metabolights_utils/commands/model/model_create.py
metabolights_utils/commands/model/model_explain.py
metabolights_utils/commands/public/__init__.py
metabolights_utils/commands/public/public_cli.py
metabolights_utils/commands/public/public_describe.py
metabolights_utils/commands/public/public_download.py
metabolights_utils/commands/public/public_list.py
metabolights_utils/commands/public/public_remove.py
metabolights_utils/commands/public/public_search.py
metabolights_utils/commands/submission/__init__.py
metabolights_utils/commands/submission/model.py
metabolights_utils/commands/submission/submission_cli.py
metabolights_utils/commands/submission/submission_create_assay.py
metabolights_utils/commands/submission/submission_delete_assay.py
metabolights_utils/commands/submission/submission_describe.py
metabolights_utils/commands/submission/submission_download.py
metabolights_utils/commands/submission/submission_list.py
metabolights_utils/commands/submission/submission_login.py
metabolights_utils/commands/submission/submission_upload.py
metabolights_utils/commands/submission/submission_validate.py
metabolights_utils/commands/submission/utils.py
metabolights_utils/isatab/__init__.py
metabolights_utils/isatab/reader.py
metabolights_utils/isatab/writer.py
metabolights_utils/isatab/default/__init__.py
metabolights_utils/isatab/default/assay_file.py
metabolights_utils/isatab/default/assignment_file.py
metabolights_utils/isatab/default/base_isa_file.py
metabolights_utils/isatab/default/base_isa_table_file.py
metabolights_utils/isatab/default/factory.py
metabolights_utils/isatab/default/investigation_file.py
metabolights_utils-1.4.18.dist-info/licenses/LICENSE
metabolights_utils-1.4.18.dist-info/METADATA
metabolights_utils-1.4.18.dist-info/WHEEL
metabolights_utils-1.4.18.dist-info/entry_points.txt
metabolights_utils-1.4.18.dist-info/top_level.txt
metabolights_utils-1.4.18.dist-info/RECORD
