Metadata-Version: 2.4
Name: metabolights-utils
Version: 1.4.18
Summary: MetaboLights open metabolomics data repository utility tools and API.
Author-email: MetaboLights Team <metabolights-dev@ebi.ac.uk>
License-Expression: Apache-2.0
Project-URL: Homepage, https://github.com/EBI-Metabolights/metabolights-utils
Project-URL: Repository, https://github.com/EBI-Metabolights/metabolights-utils
Keywords: metabolights,metabolomics,ISA data model,mtbls
Classifier: Development Status :: 5 - Production/Stable
Classifier: Environment :: Console
Classifier: Intended Audience :: Developers
Classifier: Intended Audience :: Science/Research
Classifier: Programming Language :: Python
Classifier: Programming Language :: Python :: 3.12
Classifier: Topic :: Software Development :: Libraries :: Python Modules
Classifier: Topic :: File Formats
Classifier: Topic :: Scientific/Engineering :: Bio-Informatics
Classifier: Topic :: Scientific/Engineering :: Chemistry
Classifier: Topic :: Utilities
Requires-Python: <4,>=3.9
License-File: LICENSE
Requires-Dist: pydantic>=2.11.7
Requires-Dist: pydantic-settings>=2.0.3
Requires-Dist: unidecode>=1.3.8
Requires-Dist: jsonschema>=4.24.0
Requires-Dist: click>=8.1.7
Requires-Dist: beautifulsoup4>=4.12.3
Requires-Dist: jsonpath-ng>=1.7.0
Requires-Dist: httpx>=0.27.0
Dynamic: license-file
